human_typer/__init__.py
human_typer/human_typer.py
human_typer/keyboard_helper.py
human_typer-1.1.0.dist-info/licenses/LICENSE
human_typer-1.1.0.dist-info/METADATA
human_typer-1.1.0.dist-info/WHEEL
human_typer-1.1.0.dist-info/top_level.txt
human_typer-1.1.0.dist-info/RECORD
