Metadata-Version: 2.4
Name: human_typer
Version: 1.1.0
Summary: Python package to simulate human keyboard typing
Home-page: https://github.com/UnMars/human_typer
Author: UnMars
Author-email: guillaume_roboam@hotmail.fr
Maintainer: UnMars
License: MIT
Project-URL: Homepage, https://github.com/UnMars/human_typer
Project-URL: Repository, https://github.com/UnMars/human_typer
Project-URL: Issues, https://github.com/UnMars/human_typer/issues
Keywords: human,typing,bot,keyboard,selenium,automation
Classifier: Development Status :: 5 - Production/Stable
Classifier: Intended Audience :: Developers
Classifier: License :: OSI Approved :: MIT License
Classifier: Operating System :: OS Independent
Classifier: Programming Language :: Python
Classifier: Programming Language :: Python :: 2
Classifier: Programming Language :: Python :: 2.7
Classifier: Programming Language :: Python :: 3
Classifier: Programming Language :: Python :: 3.5
Classifier: Programming Language :: Python :: 3.6
Classifier: Programming Language :: Python :: 3.7
Classifier: Programming Language :: Python :: 3.8
Classifier: Programming Language :: Python :: 3.9
Classifier: Programming Language :: Python :: 3.10
Classifier: Programming Language :: Python :: 3.11
Classifier: Programming Language :: Python :: 3.12
Classifier: Topic :: Software Development :: Testing
Classifier: Topic :: Software Development :: Libraries :: Python Modules
Requires-Python: >=2.7, !=3.0.*, !=3.1.*, !=3.2.*, !=3.3.*, !=3.4.*
License-File: LICENSE
Requires-Dist: keyboard>=0.13.5
Requires-Dist: selenium>=3.0.0
Provides-Extra: dev
Requires-Dist: pytest>=6.0; extra == "dev"
Requires-Dist: black>=21.0; extra == "dev"
Requires-Dist: flake8>=3.8; extra == "dev"
Provides-Extra: playwright
Requires-Dist: playwright>=1.40.0; extra == "playwright"
Dynamic: author-email
Dynamic: home-page
Dynamic: license-file
Dynamic: requires-python
